nbopen/__init__.py
nbopen/__main__.py
nbopen/application-x-ipynb+json.xml
nbopen/install_win.py
nbopen/install_xdg.py
nbopen/nbopen.desktop
nbopen/nbopen.py
nbopen/icons/ipynb_icon_128x128.png
nbopen/icons/ipynb_icon_16x16.png
nbopen/icons/ipynb_icon_24x24.png
nbopen/icons/ipynb_icon_256x256.png
nbopen/icons/ipynb_icon_32x32.png
nbopen/icons/ipynb_icon_48x48.png
nbopen/icons/ipynb_icon_512x512.png
nbopen/icons/ipynb_icon_64x64.png
nbopen-0.7.dist-info/entry_points.txt
nbopen-0.7.dist-info/LICENSE
nbopen-0.7.dist-info/WHEEL
nbopen-0.7.dist-info/METADATA
nbopen-0.7.dist-info/RECORD
