Metadata-Version: 2.1
Name: nbopen
Version: 0.7
Summary: Open a notebook from the command line in the best available server
Author-email: Thomas Kluyver <thomas@kluyver.me.uk>
Requires-Python: >=3.5
Classifier: License :: OSI Approved :: BSD License
Classifier: Programming Language :: Python :: 3
Classifier: Framework :: Jupyter
Requires-Dist: notebook>=7
Requires-Dist: nbformat
Project-URL: Source, https://github.com/takluyver/nbopen
